aimms_openapi_client/__init__.py
aimms_openapi_client/api_client.py
aimms_openapi_client/api_response.py
aimms_openapi_client/configuration.py
aimms_openapi_client/exceptions.py
aimms_openapi_client/py.typed
aimms_openapi_client/rest.py
aimms_openapi_client/api/__init__.py
aimms_openapi_client/api/application_api.py
aimms_openapi_client/api/authentication_api.py
aimms_openapi_client/api/customization_api.py
aimms_openapi_client/api/launching_api.py
aimms_openapi_client/api/portal_api.py
aimms_openapi_client/api/publishing_api.py
aimms_openapi_client/api/server_api.py
aimms_openapi_client/api/session_api.py
aimms_openapi_client/api/storage_api.py
aimms_openapi_client/api/task_api.py
aimms_openapi_client/models/__init__.py
aimms_openapi_client/models/aimms_version.py
aimms_openapi_client/models/aimms_version_list.py
aimms_openapi_client/models/api_key_list.py
aimms_openapi_client/models/app_instance_id.py
aimms_openapi_client/models/app_name_version.py
aimms_openapi_client/models/application_modifiable.py
aimms_openapi_client/models/current_user_info.py
aimms_openapi_client/models/customization_config_info.py
aimms_openapi_client/models/customization_profile.py
aimms_openapi_client/models/entity_authorization.py
aimms_openapi_client/models/entity_info.py
aimms_openapi_client/models/entity_info_list.py
aimms_openapi_client/models/environment_info.py
aimms_openapi_client/models/environment_list.py
aimms_openapi_client/models/error.py
aimms_openapi_client/models/error_message.py
aimms_openapi_client/models/launch_app_response.py
aimms_openapi_client/models/portal_app_access.py
aimms_openapi_client/models/portal_app_access_list.py
aimms_openapi_client/models/portal_app_info.py
aimms_openapi_client/models/portal_app_info_list.py
aimms_openapi_client/models/pro_aimms.py
aimms_openapi_client/models/pro_aimms_entry.py
aimms_openapi_client/models/pro_api_key.py
aimms_openapi_client/models/pro_api_key_scope.py
aimms_openapi_client/models/pro_app_category.py
AIMMScloud-0.1.2.2.dist-info/LICENSE
AIMMScloud-0.1.2.2.dist-info/METADATA
AIMMScloud-0.1.2.2.dist-info/WHEEL
AIMMScloud-0.1.2.2.dist-info/entry_points.txt
AIMMScloud-0.1.2.2.dist-info/top_level.txt
AIMMScloud-0.1.2.2.dist-info/RECORD
