Metadata-Version: 2.1
Name: AIMMScloud
Version: 0.1.2.2
Summary: Official AIMMS Python library to work with the AIMMS cloud environment
Author-email: Vincent Stangenberger <vincent.stangenberger@aimms.com>
License: MIT
Classifier: Programming Language :: Python :: 3
Classifier: License :: OSI Approved :: MIT License
Classifier: Operating System :: OS Independent
Requires-Python: >=3.11
License-File: LICENSE
Requires-Dist: pydantic>=2.10.4
Requires-Dist: urllib3>=2.3.0
Requires-Dist: python-dateutil>=2.9.0.post0
Requires-Dist: typing-extensions>=4.12.2
Provides-Extra: cli
Requires-Dist: click>=8.1.8; extra == "cli"
